setup.py
cfn_sphere_python/__init__.py
cfn_sphere_python/stack_config_helper.py
cfn_sphere_python.egg-info/PKG-INFO
cfn_sphere_python.egg-info/SOURCES.txt
cfn_sphere_python.egg-info/dependency_links.txt
cfn_sphere_python.egg-info/requires.txt
cfn_sphere_python.egg-info/top_level.txt
cfn_sphere_python.egg-info/zip-safe