Metadata-Version: 1.1
Name: cfn-sphere-python
Version: 0.2
Summary: cfn-sphere-python Python Wrapper for AWS CloudFormation management tool cfn-sphere
Home-page: https://github.com/ImmobilienScout24/cfn-sphere-python
Author: Felix Borchers
Author-email: felix.borcher@gmail.com
License: APACHE LICENCE, VERSION 2.0
Platform: UNKNOWN
Classifier: Development Status :: 4 - Beta
Classifier: Environment :: Console
Classifier: Intended Audience :: Developers
Classifier: Intended Audience :: System Administrators
Classifier: License :: OSI Approved :: Apache Software License
Classifier: Programming Language :: Python
Classifier: Topic :: System :: Systems Administration
